LICENSE
README.md
setup.cfg
setup.py
API42/__init__.py
API42/api.py
API42/parameter_queries.py
API42.egg-info/PKG-INFO
API42.egg-info/SOURCES.txt
API42.egg-info/dependency_links.txt
API42.egg-info/requires.txt
API42.egg-info/top_level.txt