Metadata-Version: 2.1
Name: API42
Version: 0.2
Summary: Wrapper for the 42 intra API
Home-page: https://github.com/ImOphen/API42
Download-URL: https://github.com/ImOphen/API42/archive/refs/tags/v0.2.tar.gz
Author: Ayman Touhami
Author-email: itsophen@gmail.com
License: MIT
Keywords: 42,Intra,API
Classifier: Development Status :: 4 - Beta
Classifier: Intended Audience :: Developers
Classifier: Topic :: Software Development :: Build Tools
Classifier: License :: OSI Approved :: MIT License
Classifier: Programming Language :: Python :: 3
Classifier: Programming Language :: Python :: 3.4
Classifier: Programming Language :: Python :: 3.5
Classifier: Programming Language :: Python :: 3.6
Classifier: Programming Language :: Python :: 3.7
Classifier: Programming Language :: Python :: 3.8
Classifier: Programming Language :: Python :: 3.9
Classifier: Programming Language :: Python :: 3.10
Classifier: Programming Language :: Python :: 3.11
License-File: LICENSE
